{"v":"5.1.4","fr":29.9700012207031,"ip":0,"op":420.000017106951,"w":1024,"h":1024,"nm":"final comp","ddd":0,"assets":[{"id":"comp_0","layers":[{"ddd":0,"ind":1,"ty":4,"nm":"Shape Layer 1","sr":1,"ks":{"o":{"a":0,"k":100,"ix":11},"r":{"a":0,"k":0,"ix":10},"p":{"a":0,"k":[640,512,0],"ix":2},"a":{"a":0,"k":[0,0,0],"ix":1},"s":{"a":0,"k":[90.886,90.886,100],"ix":6}},"ao":0,"shapes":[{"ty":"gr","it":[{"ind":0,"ty":"sh","ix":1,"ks":{"a":0,"k":{"i":[[0,0],[0,0],[0,0],[0,0]],"o":[[0,0],[0,0],[0,0],[0,0]],"v":[[-521.532,-466.518],[-528.134,446.713],[528.134,492.925],[426.908,-492.925]],"c":true},"ix":2},"nm":"Path 1","mn":"ADBE Vector Shape - Group","hd":false},{"ty":"st","c":{"a":0,"k":[0,0,0,1],"ix":3},"o":{"a":0,"k":100,"ix":4},"w":{"a":0,"k":56,"ix":5},"lc":1,"lj":1,"ml":4,"nm":"Stroke 1","mn":"ADBE Vector Graphic - Stroke","hd":false},{"ty":"tr","p":{"a":0,"k":[0,0],"ix":2},"a":{"a":0,"k":[0,0],"ix":1},"s":{"a":0,"k":[100,100],"ix":3},"r":{"a":0,"k":0,"ix":6},"o":{"a":0,"k":0,"ix":7},"sk":{"a":0,"k":0,"ix":4},"sa":{"a":0,"k":0,"ix":5},"nm":"Transform"}],"nm":"Shape 2","np":3,"cix":2,"ix":1,"mn":"ADBE Vector Group","hd":false},{"ty":"gr","it":[{"ind":0,"ty":"sh","ix":1,"ks":{"a":0,"k":{"i":[[0,0],[320,0],[0,115],[-184,0],[0,-201],[122.496,-50.745]],"o":[[0,0],[-310,0],[0,-246],[139,0],[0,86],[-34.936,14.473]],"v":[[343.978,88],[-32,395],[-434,7],[-20,-410],[291,-85],[98.504,178.745]],"c":false},"ix":2},"nm":"Path 1","mn":"ADBE Vector Shape - Group","hd":false},{"ty":"st","c":{"a":0,"k":[0,0,0,1],"ix":3},"o":{"a":0,"k":100,"ix":4},"w":{"a":0,"k":56,"ix":5},"lc":2,"lj":2,"nm":"Stroke 1","mn":"ADBE Vector Graphic - Stroke","hd":false},{"ty":"tm","s":{"a":1,"k":[{"i":{"x":[1],"y":[1]},"o":{"x":[0.167],"y":[0]},"n":["1_1_0p167_0"],"t":11.02,"s":[0],"e":[0.252]},{"i":{"x":[0.929],"y":[0.406]},"o":{"x":[0.125],"y":[0.915]},"n":["0p929_0p406_0p125_0p915"],"t":12.678,"s":[0.252],"e":[100]},{"t":52.5650021410163}],"ix":1},"e":{"a":1,"k":[{"i":{"x":[0.911],"y":[0.915]},"o":{"x":[0.312],"y":[0]},"n":["0p911_0p915_0p312_0"],"t":11,"s":[0],"e":[6.346]},{"i":{"x":[0.93],"y":[0.411]},"o":{"x":[0.179],"y":[0.908]},"n":["0p93_0p411_0p179_0p908"],"t":11.911,"s":[6.346],"e":[100]},{"t":51.0000020772726}],"ix":2},"o":{"a":0,"k":0,"ix":3},"m":1,"ix":4,"nm":"Trim Paths 1","mn":"ADBE Vector Filter - Trim","hd":false},{"ty":"tr","p":{"a":0,"k":[0,0],"ix":2},"a":{"a":0,"k":[0,0],"ix":1},"s":{"a":0,"k":[100,100],"ix":3},"r":{"a":0,"k":0,"ix":6},"o":{"a":0,"k":100,"ix":7},"sk":{"a":0,"k":0,"ix":4},"sa":{"a":0,"k":0,"ix":5},"nm":"Transform"}],"nm":"Shape 1","np":4,"cix":2,"ix":2,"mn":"ADBE Vector Group","hd":false}],"ip":0,"op":431.00001755499,"st":11.0000004480392,"bm":0},{"ddd":0,"ind":2,"ty":4,"nm":"Layer 2/Asperand for animation Outlines","sr":1,"ks":{"o":{"a":0,"k":100,"ix":11},"r":{"a":0,"k":0,"ix":10},"p":{"a":0,"k":[640,512,0],"ix":2},"a":{"a":0,"k":[640,512,0],"ix":1},"s":{"a":0,"k":[90.886,90.886,100],"ix":6}},"ao":0,"hasMask":true,"masksProperties":[{"inv":false,"mode":"n","pt":{"a":0,"k":{"i":[[0,0],[114,16],[-4,183],[-86,-10],[13.324,-157.466],[22.794,39.363],[-14.219,27.366]],"o":[[0,0],[-114,-16],[4,-183],[86,10],[-11,130],[-35.9,-61.994],[26.284,-50.588]],"v":[[857,622],[591,727],[369,492],[633,252],[840,463],[677,596],[727.387,361.953]],"c":false},"ix":1},"o":{"a":0,"k":100,"ix":3},"x":{"a":0,"k":0,"ix":4},"nm":"Mask 1"}],"ef":[{"ty":22,"nm":"Stroke","np":13,"mn":"ADBE Stroke","ix":1,"en":1,"ef":[{"ty":10,"nm":"Path","mn":"ADBE Stroke-0001","ix":1,"v":{"a":0,"k":0,"ix":1}},{"ty":7,"nm":"All Masks","mn":"ADBE Stroke-0010","ix":2,"v":{"a":0,"k":1,"ix":2}},{"ty":7,"nm":"Stroke Sequentially","mn":"ADBE Stroke-0011","ix":3,"v":{"a":0,"k":1,"ix":3}},{"ty":2,"nm":"Color","mn":"ADBE Stroke-0002","ix":4,"v":{"a":0,"k":[1,1,1,1],"ix":4}},{"ty":0,"nm":"Brush Size","mn":"ADBE Stroke-0003","ix":5,"v":{"a":0,"k":34.2,"ix":5}},{"ty":0,"nm":"Brush Hardness","mn":"ADBE Stroke-0004","ix":6,"v":{"a":0,"k":0.95,"ix":6}},{"ty":0,"nm":"Opacity","mn":"ADBE Stroke-0005","ix":7,"v":{"a":0,"k":1,"ix":7}},{"ty":0,"nm":"Start","mn":"ADBE Stroke-0008","ix":8,"v":{"a":0,"k":0,"ix":8}},{"ty":0,"nm":"End","mn":"ADBE Stroke-0009","ix":9,"v":{"a":1,"k":[{"i":{"x":[0.266],"y":[1]},"o":{"x":[0.107],"y":[0.639]},"n":["0p266_1_0p107_0p639"],"t":51,"s":[0],"e":[100]},{"t":80.1487532645255}],"ix":9}},{"ty":7,"nm":"Spacing","mn":"ADBE Stroke-0006","ix":10,"v":{"a":0,"k":0,"ix":10}},{"ty":7,"nm":"Paint Style","mn":"ADBE Stroke-0007","ix":11,"v":{"a":0,"k":3,"ix":11}}]}],"shapes":[{"ty":"gr","it":[{"ind":0,"ty":"sh","ix":1,"ks":{"a":0,"k":{"i":[[-54.618,0],[-7.39,32.81],[19.358,22.918],[16.501,-8.001],[7.498,-18.874]],"o":[[39.228,0],[5.748,-25.518],[-12.391,-14.67],[-19.09,9.257],[-12.596,31.705]],"v":[[-24,83.346],[41.766,10.056],[41.415,-71.182],[-12.396,-79.3],[-50.438,-30.272]],"c":true},"ix":2},"nm":"Path 1","mn":"ADBE Vector Shape - Group","hd":false},{"ind":1,"ty":"sh","ix":2,"ks":{"a":0,"k":{"i":[[-1.343,9.398],[3.314,-29.765],[4.272,-17.678],[6.01,-24.872],[1.341,-8.056],[-23.301,10.665],[-10.949,22.846],[29.366,45.659],[84.276,-54.451],[-40.678,-97.738],[-95.169,19.307],[-21.864,12.004],[-16.595,-10.07],[26.25,-10.174],[79.196,73.599],[-51.543,99.868],[-110.316,-2.599],[8.053,-135.59],[46.127,-37.304],[34.279,52.266],[39.136,46.837],[-21.538,45.779],[-57.453,-8.578],[-5.17,-3.15],[-11.328,-4.562]],"o":[[4.092,-28.64],[-2.015,18.1],[-6.009,24.873],[-2.349,9.727],[-6.714,29.537],[23.611,-10.807],[23.052,-48.091],[-58.405,-90.806],[-87.539,56.558],[40.126,96.415],[24.457,-4.961],[20.485,-11.248],[47.28,28.692],[-99.378,38.513],[-84.662,-78.681],[51.363,-99.521],[128.654,3.032],[-3.499,58.91],[-41.977,33.948],[-40.715,34.555],[-35.104,-42.01],[23.029,-48.949],[8.808,1.316],[12.971,7.903],[14.735,5.934]],"v":[[89.211,-127.825],[142.24,-116.558],[129.063,-62.018],[110.693,11.805],[102.638,49.399],[140.104,73.089],[192.204,15.973],[187.204,-140.589],[-94.621,-181.663],[-182.277,91.397],[64.579,198.177],[134.263,172.422],[207.073,149.596],[116.044,239.064],[-185.767,188.387],[-228.376,-122.524],[39.331,-274.978],[271.867,-45.356],[195.279,106.166],[40.957,103.287],[-110.605,107.476],[-114.728,-53.912],[14.927,-137.82],[44.705,-126.018],[69.073,-110.372]],"c":true},"ix":2},"nm":"Path 2","mn":"ADBE Vector Shape - Group","hd":false},{"ty":"mm","mm":1,"nm":"Merge Paths 1","mn":"ADBE Vector Filter - Merge","hd":false},{"ty":"fl","c":{"a":0,"k":[0,0,0,1],"ix":4},"o":{"a":0,"k":100,"ix":5},"r":1,"nm":"Fill 1","mn":"ADBE Vector Graphic - Fill","hd":false},{"ty":"tr","p":{"a":0,"k":[594.991,495.531],"ix":2},"a":{"a":0,"k":[0,0],"ix":1},"s":{"a":0,"k":[100,100],"ix":3},"r":{"a":0,"k":0,"ix":6},"o":{"a":0,"k":100,"ix":7},"sk":{"a":0,"k":0,"ix":4},"sa":{"a":0,"k":0,"ix":5},"nm":"Transform"}],"nm":"Group 1","np":4,"cix":2,"ix":1,"mn":"ADBE Vector Group","hd":false}],"ip":11.0000004480392,"op":431.00001755499,"st":11.0000004480392,"bm":0},{"ddd":0,"ind":3,"ty":4,"nm":"Layer 2/Asperand for animation Outlines 2","sr":1,"ks":{"o":{"a":0,"k":100,"ix":11},"r":{"a":0,"k":0,"ix":10},"p":{"a":0,"k":[640,512,0],"ix":2},"a":{"a":0,"k":[640,512,0],"ix":1},"s":{"a":0,"k":[90.886,90.886,100],"ix":6}},"ao":0,"hasMask":true,"masksProperties":[{"inv":false,"mode":"n","pt":{"a":0,"k":{"i":[[0,0],[101,23],[-2,-81],[-124.5,177.5]],"o":[[0,0],[-52,-14.5],[0.913,36.989],[84.493,-120.462]],"v":[[670.5,473],[592,383.5],[497,542.5],[672,501.5]],"c":false},"ix":1},"o":{"a":0,"k":100,"ix":3},"x":{"a":0,"k":0,"ix":4},"nm":"Mask 1"}],"ef":[{"ty":22,"nm":"Stroke","np":13,"mn":"ADBE Stroke","ix":1,"en":1,"ef":[{"ty":10,"nm":"Path","mn":"ADBE Stroke-0001","ix":1,"v":{"a":0,"k":0,"ix":1}},{"ty":7,"nm":"All Masks","mn":"ADBE Stroke-0010","ix":2,"v":{"a":0,"k":1,"ix":2}},{"ty":7,"nm":"Stroke Sequentially","mn":"ADBE Stroke-0011","ix":3,"v":{"a":0,"k":1,"ix":3}},{"ty":2,"nm":"Color","mn":"ADBE Stroke-0002","ix":4,"v":{"a":0,"k":[1,1,1,1],"ix":4}},{"ty":0,"nm":"Brush Size","mn":"ADBE Stroke-0003","ix":5,"v":{"a":0,"k":37,"ix":5}},{"ty":0,"nm":"Brush Hardness","mn":"ADBE Stroke-0004","ix":6,"v":{"a":0,"k":0.95,"ix":6}},{"ty":0,"nm":"Opacity","mn":"ADBE Stroke-0005","ix":7,"v":{"a":0,"k":1,"ix":7}},{"ty":0,"nm":"Start","mn":"ADBE Stroke-0008","ix":8,"v":{"a":0,"k":0,"ix":8}},{"ty":0,"nm":"End","mn":"ADBE Stroke-0009","ix":9,"v":{"a":1,"k":[{"i":{"x":[0.018],"y":[0.779]},"o":{"x":[0.799],"y":[0.336]},"n":["0p018_0p779_0p799_0p336"],"t":72,"s":[0],"e":[97]},{"t":97.2225039599536}],"ix":9}},{"ty":7,"nm":"Spacing","mn":"ADBE Stroke-0006","ix":10,"v":{"a":0,"k":0,"ix":10}},{"ty":7,"nm":"Paint Style","mn":"ADBE Stroke-0007","ix":11,"v":{"a":0,"k":3,"ix":11}}]}],"shapes":[{"ty":"gr","it":[{"ind":0,"ty":"sh","ix":1,"ks":{"a":0,"k":{"i":[[-54.618,0],[-7.39,32.81],[19.358,22.918],[16.501,-8.001],[7.498,-18.874]],"o":[[39.228,0],[5.748,-25.518],[-12.391,-14.67],[-19.09,9.257],[-12.596,31.705]],"v":[[-24,83.346],[41.766,10.056],[41.415,-71.182],[-12.396,-79.3],[-50.438,-30.272]],"c":true},"ix":2},"nm":"Path 1","mn":"ADBE Vector Shape - Group","hd":false},{"ind":1,"ty":"sh","ix":2,"ks":{"a":0,"k":{"i":[[-1.343,9.398],[3.314,-29.765],[4.272,-17.678],[6.01,-24.872],[1.341,-8.056],[-23.301,10.665],[-10.949,22.846],[29.366,45.659],[84.276,-54.451],[-40.678,-97.738],[-95.169,19.307],[-21.864,12.004],[-16.595,-10.07],[26.25,-10.174],[79.196,73.599],[-51.543,99.868],[-110.316,-2.599],[8.053,-135.59],[46.127,-37.304],[34.279,52.266],[39.136,46.837],[-21.538,45.779],[-57.453,-8.578],[-5.17,-3.15],[-11.328,-4.562]],"o":[[4.092,-28.64],[-2.015,18.1],[-6.009,24.873],[-2.349,9.727],[-6.714,29.537],[23.611,-10.807],[23.052,-48.091],[-58.405,-90.806],[-87.539,56.558],[40.126,96.415],[24.457,-4.961],[20.485,-11.248],[47.28,28.692],[-99.378,38.513],[-84.662,-78.681],[51.363,-99.521],[128.654,3.032],[-3.499,58.91],[-41.977,33.948],[-40.715,34.555],[-35.104,-42.01],[23.029,-48.949],[8.808,1.316],[12.971,7.903],[14.735,5.934]],"v":[[89.211,-127.825],[142.24,-116.558],[129.063,-62.018],[110.693,11.805],[102.638,49.399],[140.104,73.089],[192.204,15.973],[187.204,-140.589],[-94.621,-181.663],[-182.277,91.397],[64.579,198.177],[134.263,172.422],[207.073,149.596],[116.044,239.064],[-185.767,188.387],[-228.376,-122.524],[39.331,-274.978],[271.867,-45.356],[195.279,106.166],[40.957,103.287],[-110.605,107.476],[-114.728,-53.912],[14.927,-137.82],[44.705,-126.018],[69.073,-110.372]],"c":true},"ix":2},"nm":"Path 2","mn":"ADBE Vector Shape - Group","hd":false},{"ty":"mm","mm":1,"nm":"Merge Paths 1","mn":"ADBE Vector Filter - Merge","hd":false},{"ty":"fl","c":{"a":0,"k":[0,0,0,1],"ix":4},"o":{"a":0,"k":100,"ix":5},"r":1,"nm":"Fill 1","mn":"ADBE Vector Graphic - Fill","hd":false},{"ty":"tr","p":{"a":0,"k":[594.991,495.531],"ix":2},"a":{"a":0,"k":[0,0],"ix":1},"s":{"a":0,"k":[100,100],"ix":3},"r":{"a":0,"k":0,"ix":6},"o":{"a":0,"k":100,"ix":7},"sk":{"a":0,"k":0,"ix":4},"sa":{"a":0,"k":0,"ix":5},"nm":"Transform"}],"nm":"Group 1","np":4,"cix":2,"ix":1,"mn":"ADBE Vector Group","hd":false}],"ip":11.0000004480392,"op":431.00001755499,"st":11.0000004480392,"bm":0}]}],"layers":[{"ddd":0,"ind":1,"ty":0,"nm":"Main Comp 2","refId":"comp_0","sr":1,"ks":{"o":{"a":0,"k":100,"ix":11},"r":{"a":0,"k":0,"ix":10},"p":{"a":0,"k":[556,540,0],"ix":2},"a":{"a":0,"k":[640,512,0],"ix":1},"s":{"a":0,"k":[110,110,100],"ix":6}},"ao":0,"ef":[{"ty":21,"nm":"Fill","np":9,"mn":"ADBE Fill","ix":1,"en":1,"ef":[{"ty":10,"nm":"Fill Mask","mn":"ADBE Fill-0001","ix":1,"v":{"a":0,"k":0,"ix":1}},{"ty":7,"nm":"All Masks","mn":"ADBE Fill-0007","ix":2,"v":{"a":0,"k":0,"ix":2}},{"ty":2,"nm":"Color","mn":"ADBE Fill-0002","ix":3,"v":{"a":0,"k":[1,1,1,1],"ix":3}},{"ty":7,"nm":"Invert","mn":"ADBE Fill-0006","ix":4,"v":{"a":0,"k":0,"ix":4}},{"ty":0,"nm":"Horizontal Feather","mn":"ADBE Fill-0003","ix":5,"v":{"a":0,"k":0,"ix":5}},{"ty":0,"nm":"Vertical Feather","mn":"ADBE Fill-0004","ix":6,"v":{"a":0,"k":0,"ix":6}},{"ty":0,"nm":"Opacity","mn":"ADBE Fill-0005","ix":7,"v":{"a":0,"k":1,"ix":7}}]}],"w":1280,"h":1024,"ip":1.00000004073083,"op":421.000017147682,"st":1.00000004073083,"bm":0}],"markers":[]}